{"name":"ProblemaPersiste2","identifier":"O8QU7D3CHE","description":null,"slotTypeName":"SimOuNao","obfuscationSetting":null,"valueElicitationSetting":{"slotCaptureSetting":{"codeHook":null,"captureResponse":null,"captureNextStep":{"intent":{"name":null,"slots":null},"dialogAction":{"type":"EvaluateConditional","slotToElicit":null,"suppressNextMessage":null},"sessionAttributes":null},"captureConditional":{"isActive":true,"defaultBranch":{"response":null,"nextStep":{"intent":{"name":null,"slots":null},"dialogAction":{"type":"ElicitIntent","slotToElicit":null,"suppressNextMessage":null},"sessionAttributes":null}},"conditionalBranches":[{"name":"Sim","response":null,"condition":{"expressionString":"{ProblemaPersiste2} = \"sim\""},"nextStep":{"intent":{"name":null,"slots":null},"dialogAction":{"type":"ElicitSlot","slotToElicit":"UsarOutroTelefone","suppressNextMessage":null},"sessionAttributes":null}},{"name":"Nao","response":{"messageGroupsList":[{"message":{"ssmlMessage":null,"customPayload":null,"plainTextMessage":{"value":"Ótimo! Parece que o problema foi resolvido ajustando o volume do telefone."},"imageResponseCard":null},"variations":null}],"allowInterrupt":true},"condition":{"expressionString":"{ProblemaPersiste2} = \"não\""},"nextStep":{"intent":{"name":null,"slots":null},"dialogAction":{"type":"CloseIntent","slotToElicit":null,"suppressNextMessage":null},"sessionAttributes":null}}]},"failureResponse":null,"failureNextStep":{"intent":{"name":"FallbackIntent","slots":null},"dialogAction":{"type":"StartIntent","slotToElicit":null,"suppressNextMessage":null},"sessionAttributes":null},"failureConditional":null,"elicitationCodeHook":{"enableCodeHookInvocation":true,"invocationLabel":null}},"promptSpecification":{"messageGroupsList":[{"message":{"ssmlMessage":null,"customPayload":null,"plainTextMessage":null,"imageResponseCard":{"title":"Continua tendo problema?","buttonsList":[{"value":"sim","text":"Sim"},{"value":"não","text":"Não"}],"subtitle":null,"imageUrl":null}},"variations":null}],"maxRetries":4,"allowInterrupt":true,"messageSelectionStrategy":"Random","promptAttemptsSpecification":{"Retry3":{"allowedInputTypes":{"allowAudioInput":true,"allowDTMFInput":true},"audioAndDTMFInputSpecification":{"dtmfSpecification":{"maxLength":513,"deletionCharacter":"*","endCharacter":"#","endTimeoutMs":5000},"startTimeoutMs":4000,"audioSpecification":{"maxLengthMs":15000,"endTimeoutMs":640}},"allowInterrupt":true,"textInputSpecification":{"startTimeoutMs":30000}},"Retry2":{"allowedInputTypes":{"allowAudioInput":true,"allowDTMFInput":true},"audioAndDTMFInputSpecification":{"dtmfSpecification":{"maxLength":513,"deletionCharacter":"*","endCharacter":"#","endTimeoutMs":5000},"startTimeoutMs":4000,"audioSpecification":{"maxLengthMs":15000,"endTimeoutMs":640}},"allowInterrupt":true,"textInputSpecification":{"startTimeoutMs":30000}},"Retry4":{"allowedInputTypes":{"allowAudioInput":true,"allowDTMFInput":true},"audioAndDTMFInputSpecification":{"dtmfSpecification":{"maxLength":513,"deletionCharacter":"*","endCharacter":"#","endTimeoutMs":5000},"startTimeoutMs":4000,"audioSpecification":{"maxLengthMs":15000,"endTimeoutMs":640}},"allowInterrupt":true,"textInputSpecification":{"startTimeoutMs":30000}},"Retry1":{"allowedInputTypes":{"allowAudioInput":true,"allowDTMFInput":true},"audioAndDTMFInputSpecification":{"dtmfSpecification":{"maxLength":513,"deletionCharacter":"*","endCharacter":"#","endTimeoutMs":5000},"startTimeoutMs":4000,"audioSpecification":{"maxLengthMs":15000,"endTimeoutMs":640}},"allowInterrupt":true,"textInputSpecification":{"startTimeoutMs":30000}},"Initial":{"allowedInputTypes":{"allowAudioInput":true,"allowDTMFInput":true},"audioAndDTMFInputSpecification":{"dtmfSpecification":{"maxLength":513,"deletionCharacter":"*","endCharacter":"#","endTimeoutMs":5000},"startTimeoutMs":4000,"audioSpecification":{"maxLengthMs":15000,"endTimeoutMs":640}},"allowInterrupt":true,"textInputSpecification":{"startTimeoutMs":30000}}}},"slotConstraint":"Required","defaultValueSpecification":null,"sampleUtterances":null,"waitAndContinueSpecification":null},"multipleValuesSetting":null}